{
  "dimension": "D7",
  "dimension_name": "结尾回收与整体完成度",
  "score": 4.2,
  "weight": 5,
  "checks": [
    {
      "id": "END1",
      "score": 4.2,
      "comment": "主线谜团（姐姐生死、离线证人真相、系统伦理）全部在结尾回收：E08-S01姐妹重逢确认姐姐存活，E08-S02许若安讲述两年前冲突，E08-S04孟远舟被控制，E08-S05-06删除数字副本。"
    },
    {
      "id": "END2",
      "score": 4.0,
      "comment": "关键人物弧光闭合：许若清从执着录音到关机放下，许若安从躲避到出庭，周望删除母亲回声，顾峥完成证据链。陆鸣的动机（爱上数字副本）在E07-S05遗书中揭示，但未在结尾再次提及，略有弱化。"
    },
    {
      "id": "END3",
      "score": 4.5,
      "comment": "主题落点清晰：科技伦理——最终选择删除数字副本，回归现实生活；姐妹和解，强调人的情感不可替代。"
    },
    {
      "id": "END4",
      "score": 4.0,
      "comment": "悬疑收束：所有主要问题（许若安是否活着、管理员身份、陆鸣动机、系统监听）均有答案。但口罩男的动机和身份未明确交代，属于小缺口。"
    },
    {
      "id": "END5",
      "score": 3.8,
      "comment": "结尾节奏：E08中许若安讲述真相略偏口述解释，但情节紧凑，姐妹重逢情感饱满，结局场景（海边对话）有留白，整体节奏合理。"
    },
    {
      "id": "END6",
      "score": 4.0,
      "comment": "开放性可控：没有留下重大未解悬念，新生活开始属于开放式结局，但控制得当，不破坏完成感。"
    },
    {
      "id": "END7",
      "score": 4.2,
      "comment": "前后呼应：设定了多个伏笔并回收，如硬盘密码“我还没死”在E07-S06暗示姐姐可能活着，E08-S01确认。但密码来源未直接解释，略减分。"
    },
    {
      "id": "END8",
      "score": 4.3,
      "comment": "整体结构完整：8集剧本有清晰的三幕结构，结尾收束有力，人物状态合理，主题落地。"
    }
  ],
  "triggered_score_caps": [],
  "score_reason": "剧本结尾回收了核心主线、关键悬疑、人物弧光和主题，完成度较高。扣分原因：口罩男的动机未交代（小缺口），硬盘密码'我还没死'的来源未在结尾明确解释（虽是伏笔但需观众自行补全），陆鸣的遗书揭示在E07但结尾未再次点题。总体成熟可开发，评分4.2。",
  "positive_evidence": [
    "许若安在E08-S01-S02完整讲述两年前冲突和逃离，揭示所有真相",
    "孟远舟在E08-S04被顾峥证据链控制，主线冲突解决",
    "姐妹在E08-S05-S06决定删除数字副本，伦理主题落地",
    "许若清在E08-S08关机不再录音，人物弧光闭合",
    "主创在材料中列出setup-payoff map，超过30个伏笔得到回收"
  ],
  "negative_evidence": [
    "口罩男人的身份和动机在结尾未交代，仅在E02-S06/E02-S07出现后消失",
    "硬盘密码'我还没死'的出处未在结尾解释（E01-S07/E02-S08），可能造成观众疑惑",
    "陆鸣的遗书在E07-S05揭示，但结尾未再呼应其情感动机"
  ],
  "suggestions": [
    "在E08-S02许若安讲述中顺带提及口罩男人身份（如保安或调查员），闭合线索",
    "在E08-S05姐妹对话中提及'我还没死'的由来，例如许若安曾对妹妹说过这句话，强化密码合理性",
    "在E08-S07周望卸载母亲回声的场景中，可简短回顾陆鸣的遗书，加深角色羁绊"
  ],
  "low_score_diagnosis": null
}
