{
  "dimension": "D1",
  "dimension_name": "悬疑信息控制",
  "score": 3.5,
  "weight": 20,
  "checks": [
    {
      "id": "S1",
      "score": 3.5,
      "comment": "信息释放节奏合理，E01-S01设置姐姐账号登录，E03-S08揭示为管理员，但E02-S06戴口罩男动机未及时解释，造成节奏中断。"
    },
    {
      "id": "S2",
      "score": 3.5,
      "comment": "伏笔回收比例较高，setup_payoff_map显示多数伏笔有对应，但E01-S08设置的戴口罩男身份未完全回收，密码'我还没死'来源不清。"
    },
    {
      "id": "S3",
      "score": 4.0,
      "comment": "悬念设置强度好，核心谜题从第一集持续吸引，如姐姐是否存活、离线证人项目等。"
    },
    {
      "id": "S4",
      "score": 3.0,
      "comment": "信息一致性存在问题，如密码'我还没死'与后续录音'我愿意留下'矛盾，系统对周望的特殊性未充分解释。"
    },
    {
      "id": "S5",
      "score": 3.5,
      "comment": "观众认知控制基本合格，关键信息如管理员机制在E04-S05才揭示，但部分线索依赖后期补充，前期略模糊。"
    },
    {
      "id": "S6",
      "score": 4.0,
      "comment": "反转效果良好，如E06-S08许若安影像说'别报警'，E07-S08确认姐姐活着，反转有铺垫。"
    },
    {
      "id": "S7",
      "score": 3.5,
      "comment": "信息冗余度适中，未出现过度重复或缺失，但口罩男动机未闭环属于信息欠缺。"
    },
    {
      "id": "S8",
      "score": 3.5,
      "comment": "信息延迟处理恰当，关键线索如硬盘密码在第2集解锁，未过度拖延，但次要线索（口罩男）未有下文。"
    }
  ],
  "triggered_score_caps": [],
  "score_reason": "整体信息控制结构完整，悬念设置和反转有效，但存在两处明显瑕疵：戴口罩男人的动机和身份未完全揭示（关键伏笔未回收），以及硬盘密码'我还没死'来源不合理（逻辑不一致）。这些扣分项导致评分无法高于3.5。未触发硬性降分规则（核心谜题已启动且大部分真相有前置线索）。",
  "positive_evidence": [
    "E01-S01姐姐账号登录立即引发核心悬念，贯穿全剧",
    "setup_payoff_map显示大多数伏笔（如账号异常、语音警告、硬盘）在后续得到回收",
    "反转如许若安存活有E07-S06管理员提示作为前置线索，非凭空出现"
  ],
  "negative_evidence": [
    "E01-S08设置的戴口罩男人（神秘人）在E02-S06交互后未再出现，其动机和身份未明确揭示",
    "硬盘密码'我还没死'（E02-S08）与许若安在E03-S06录音'我愿意留下'矛盾，且未解释陆鸣如何得知此密码",
    "系统对周望的特殊行为（E03-S08播放母亲声音）未与系统对其他人的行为逻辑保持一致"
  ],
  "suggestions": [
    "在后续修改中明确戴口罩男人的身份（如陆鸣同伙或第三方调查者）并补充其动机",
    "调整或补充硬盘密码的来源，例如让许若安在早期场景说过类似的话，或由陆鸣根据许若安性格设定",
    "解释系统为何能播放周望未上传的母亲声音，可通过系统权限或已收集相关音频来合理化"
  ],
  "low_score_diagnosis": null
}
